AUTHORS.rst
CHANGELOG.rst
LICENSE
MANIFEST.in
README.rst
setup.py
django_navbuilder.egg-info/PKG-INFO
django_navbuilder.egg-info/SOURCES.txt
django_navbuilder.egg-info/dependency_links.txt
django_navbuilder.egg-info/not-zip-safe
django_navbuilder.egg-info/requires.txt
django_navbuilder.egg-info/top_level.txt
navbuilder/__init__.py
navbuilder/__init__.pyc
navbuilder/admin.py
navbuilder/admin.pyc
navbuilder/forms.py
navbuilder/forms.pyc
navbuilder/models.py
navbuilder/models.pyc
navbuilder/urls.py
navbuilder/urls.pyc
navbuilder/views.py
navbuilder/views.pyc
navbuilder/api/__init__.py
navbuilder/migrations/0001_initial.py
navbuilder/migrations/0002_auto_20160907_0317.py
navbuilder/migrations/0003_auto_20161017_1414.py
navbuilder/migrations/0004_menuitem_root_menu.py
navbuilder/migrations/0005_menuitem_root_menu_migrate.py
navbuilder/migrations/__init__.py
navbuilder/templates/navbuilder/menu_detail.html
navbuilder/templates/navbuilder/menu_list.html
navbuilder/templates/navbuilder/inclusion_tags/breadcrumbs.html
navbuilder/templates/navbuilder/inclusion_tags/menu_detail.html
navbuilder/templates/navbuilder/inclusion_tags/menuitem_detail.html
navbuilder/templatetags/__init__.py
navbuilder/templatetags/__init__.pyc
navbuilder/templatetags/navbuilder_tags.py
navbuilder/templatetags/navbuilder_tags.pyc
navbuilder/tests/__init__.py
navbuilder/tests/__init__.pyc
navbuilder/tests/test_admin.py
navbuilder/tests/test_admin.pyc
navbuilder/tests/test_base.py
navbuilder/tests/test_base.pyc
navbuilder/tests/test_breadcrumbs.py
navbuilder/tests/test_breadcrumbs.pyc
navbuilder/tests/test_models.py
navbuilder/tests/test_models.pyc
navbuilder/tests/test_views.py
navbuilder/tests/test_views.pyc
navbuilder/tests/urls.py
navbuilder/tests/urls.pyc
navbuilder/tests/requirements/110.txt
navbuilder/tests/requirements/111.txt
navbuilder/tests/requirements/19.txt
navbuilder/tests/settings/110.py
navbuilder/tests/settings/110.pyc
navbuilder/tests/settings/111.py
navbuilder/tests/settings/111.pyc
navbuilder/tests/settings/19.py
navbuilder/tests/settings/19.pyc
navbuilder/tests/settings/__init__.py
navbuilder/tests/settings/__init__.pyc
navbuilder/tests/templates/base.html