Metadata-Version: 1.1
Name: django-navbuilder
Version: 0.1
Summary: Build hierarchical navigation objects from multiple link objects
Home-page: http://github.com/praekelt/django-navbuilder
Author: Praekelt Consulting
Author-email: dev@praekelt.com
License: BSD
Platform: UNKNOWN
Classifier: Programming Language :: Python
Classifier: License :: OSI Approved :: BSD License
Classifier: Operating System :: OS Independent
Classifier: Framework :: Django
Classifier: Intended Audience :: Developers
Classifier: Topic :: Internet :: WWW/HTTP :: Dynamic Content
